CHANGES.txt
MANIFEST.in
README.txt
setup.cfg
setup.py
redomino_cartasi/__init__.py
redomino_cartasi/conf.py
redomino_cartasi/models.py
redomino_cartasi/payment.py
redomino_cartasi/tests.py
redomino_cartasi/urls.py
redomino_cartasi/utils.py
redomino_cartasi/views.py
redomino_cartasi.egg-info/PKG-INFO
redomino_cartasi.egg-info/SOURCES.txt
redomino_cartasi.egg-info/dependency_links.txt
redomino_cartasi.egg-info/entry_points.txt
redomino_cartasi.egg-info/not-zip-safe
redomino_cartasi.egg-info/top_level.txt
redomino_cartasi/locale/it/LC_MESSAGES/django.mo
redomino_cartasi/locale/it/LC_MESSAGES/django.po
redomino_cartasi/templates/annulment.html
redomino_cartasi/templates/error.html
redomino_cartasi/templates/postform_cartasi.html