Metadata-Version: 1.1
Name: redomino-cartasi
Version: 0.2
Summary: Cartasi LFS processor
Home-page: http://redomino.com
Author: Davide Moro
Author-email: davide.moro@redomino.com
License: UNKNOWN
Platform: UNKNOWN
Classifier: Framework :: Django
Classifier: Programming Language :: Python
